traffic.v
// traffic light controller design file
//assuming a clock frequency of 100MHz so time period is 10ns

module traffic(
  input clk,
  input rst,
  output reg [2:0] signal1_light,
  output reg [2:0] signal2_light); // signal1_light is north-south direction road and signal2_light is east-west direction road
  
  parameter S0=2'b00; // signal1_light is green signal2_light is red
  parameter S1=2'b01; // signal1_light is yellow signal2_light is red
  parameter S2=2'b10; // signal1_light is red signal2_light is green
  parameter S3=2'b11; // signal1_light is red signal2_light is yellow
  
  reg [1:0] state,next_state;
  reg [3:0] count;
  
  parameter state1=5; // green light duration of signal1
  parameter state2=2; // yellow light duration of signal1
  parameter state3=5;// green light duration of signal2
  parameter state4=2;//yellow light duration of the signal2
  
  parameter greenlight=3'b001;
  parameter yellowlight=3'b010;
  parameter redlight=3'b100;
  
  wire [3:0] duration;
  assign duration =(state==S0)?state1:(state==S1)?state2:(state==S2)?state3:state4;
  
 
  always @(posedge clk or posedge rst)
    begin
      if(rst)
        begin
          state<=S0;		//intial let it be in S0 state
          count<=1;			//initial count is 1
        end else
          begin
            if(count==duration-1)
              begin
                state<=state+1; //move to the next state
                count<=0;		//and reset the counter
          end else begin
            count<=count+1;		// if reset is zero then increment counter by 1
          end
          end
    end
    
// determining the next state values
  always @(*)
    begin
      case(state)
        S0: begin
          next_state=(count<state1)?S0:S1; 
        end
        S1: begin
          next_state=(count<state2)?S1:S2;
        end
        S2:begin
          next_state=(count<state3)?S2:S3;
        end
        S3: begin
          next_state=(count<state4)?S3:S0;
        end
        default:next_state=S0;
      endcase
    end

// dtermining the lights for the signals on both roads.
  
  always @(*)
    begin
      case(state)
        S0: begin
          signal1_light=greenlight;
          signal2_light=redlight;
        end
        S1: begin
          signal1_light=yellowlight;
          signal2_light=redlight;
        end
        S2:begin
          signal1_light=redlight;
          signal2_light=greenlight;
        end
        S3: begin
          signal1_light=redlight;
          signal2_light=yellowlight;
        end
      endcase
        end
        endmodule

traffic_tb.v
// traffic light controller testbench file

module traffic_tb;
  reg clk,rst;
  wire [2:0] signal1_light;
  wire [2:0] signal2_light;
  
  traffic DUT(.clk(clk),.rst(rst),.signal1_light(signal1_light),.signal2_light(signal2_light));
  
  initial
    begin
      clk=1;
      forever #5 clk=~clk; // toggle clock every 5 ns (total time period is 5*2=10ns)
    end
  initial
    begin
      $dumpfile("traffic.vcd");
      $dumpvars(0,traffic_tb);
    end
  initial
    begin
      $display("Time \tSignal1 \tSignal2");
      rst=1; #20;
      rst=0;
      #(500);
      $finish;
    end
   always @(signal1_light or signal2_light) begin
     $display("%0t \t%s \t\t%s", $time,
      (signal1_light==3'b001) ?"GREEN"  :
      (signal1_light==3'b010) ?"YELLOW" :"RED",
      (signal2_light==3'b001) ?"GREEN"  :
      (signal2_light==3'b010) ?"YELLOW" :"RED");
    end
endmodule

traffic.vcd
$date
	Tue Sep 09 10:30:13 2025
$end
$version
	Icarus Verilog
$end
$timescale
	1s
$end
$scope module traffic_tb $end
$var wire 3 ! signal2_light [2:0] $end
$var wire 3 " signal1_light [2:0] $end
$var reg 1 # clk $end
$var reg 1 $ rst $end
$scope module DUT $end
$var wire 1 # clk $end
$var wire 1 $ rst $end
$var wire 4 % duration [3:0] $end
$var parameter 2 & S0 $end
$var parameter 2 ' S1 $end
$var parameter 2 ( S2 $end
$var parameter 2 ) S3 $end
$var parameter 3 * greenlight $end
$var parameter 3 + redlight $end
$var parameter 32 , state1 $end
$var parameter 32 - state2 $end
$var parameter 32 . state3 $end
$var parameter 32 / state4 $end
$var parameter 3 0 yellowlight $end
$var reg 4 1 count [3:0] $end
$var reg 2 2 next_state [1:0] $end
$var reg 3 3 signal1_light [2:0] $end
$var reg 3 4 signal2_light [2:0] $end
$var reg 2 5 state [1:0] $end
$upscope $end
$upscope $end
$enddefinitions $end
$comment Show the parameter values. $end
$dumpall
b10 0
b10 /
b101 .
b10 -
b101 ,
b100 +
b1 *
b11 )
b10 (
b1 '
b0 &
$end
#0
$dumpvars
b0 5
b100 4
b1 3
b0 2
b1 1
b101 %
1$
1#
b1 "
b100 !
$end
#5
0#
#10
1#
#15
0#
#20
b10 1
1#
0$
#25
0#
#30
b11 1
1#
#35
0#
#40
b100 1
1#
#45
0#
#50
b10 %
b10 "
b10 3
b1 2
b0 1
b1 5
1#
#55
0#
#60
b1 1
1#
#65
0#
#70
b101 %
b1 !
b1 4
b100 "
b100 3
b10 2
b0 1
b10 5
1#
#75
0#
#80
b1 1
1#
#85
0#
#90
b10 1
1#
#95
0#
#100
b11 1
1#
#105
0#
#110
b100 1
1#
#115
0#
#120
b10 %
b10 !
b10 4
b11 2
b0 1
b11 5
1#
#125
0#
#130
b1 1
1#
#135
0#
#140
b101 %
b100 !
b100 4
b1 "
b1 3
b0 2
b0 1
b0 5
1#
#145
0#
#150
b1 1
1#
#155
0#
#160
b10 1
1#
#165
0#
#170
b11 1
1#
#175
0#
#180
b100 1
1#
#185
0#
#190
b10 %
b10 "
b10 3
b1 2
b0 1
b1 5
1#
#195
0#
#200
b1 1
1#
#205
0#
#210
b101 %
b1 !
b1 4
b100 "
b100 3
b10 2
b0 1
b10 5
1#
#215
0#
#220
b1 1
1#
#225
0#
#230
b10 1
1#
#235
0#
#240
b11 1
1#
#245
0#
#250
b100 1
1#
#255
0#
#260
b10 %
b10 !
b10 4
b11 2
b0 1
b11 5
1#
#265
0#
#270
b1 1
1#
#275
0#
#280
b101 %
b100 !
b100 4
b1 "
b1 3
b0 2
b0 1
b0 5
1#
#285
0#
#290
b1 1
1#
#295
0#
#300
b10 1
1#
#305
0#
#310
b11 1
1#
#315
0#
#320
b100 1
1#
#325
0#
#330
b10 %
b10 "
b10 3
b1 2
b0 1
b1 5
1#
#335
0#
#340
b1 1
1#
#345
0#
#350
b101 %
b1 !
b1 4
b100 "
b100 3
b10 2
b0 1
b10 5
1#
#355
0#
#360
b1 1
1#
#365
0#
#370
b10 1
1#
#375
0#
#380
b11 1
1#
#385
0#
#390
b100 1
1#
#395
0#
#400
b10 %
b10 !
b10 4
b11 2
b0 1
b11 5
1#
#405
0#
#410
b1 1
1#
#415
0#
#420
b101 %
b100 !
b100 4
b1 "
b1 3
b0 2
b0 1
b0 5
1#
#425
0#
#430
b1 1
1#
#435
0#
#440
b10 1
1#
#445
0#
#450
b11 1
1#
#455
0#
#460
b100 1
1#
#465
0#
#470
b10 %
b10 "
b10 3
b1 2
b0 1
b1 5
1#
#475
0#
#480
b1 1
1#
#485
0#
#490
b101 %
b1 !
b1 4
b100 "
b100 3
b10 2
b0 1
b10 5
1#
#495
0#
#500
b1 1
1#
#505
0#
#510
b10 1
1#
#515
0#
#520
b11 1
1#
